RFM69Serial/__init__.py
RFM69Serial/device.py
RFM69Serial/packet.py
rfm69_serial-0.1.2.dist-info/LICENSE
rfm69_serial-0.1.2.dist-info/METADATA
rfm69_serial-0.1.2.dist-info/WHEEL
rfm69_serial-0.1.2.dist-info/top_level.txt
rfm69_serial-0.1.2.dist-info/RECORD
