Metadata-Version: 2.1
Name: rfm69-serial
Version: 0.1.2
Summary: A serial bridge package to connect RFM69 module to PC
Author-email: Long Pham <longpear@gmail.com>
License: GNU AFFERO GENERAL PUBLIC LICENSE
Project-URL: Homepage, https://github.com/longpear/rfm69-serial
Keywords: rfm69,serial,bridge
Classifier: License :: OSI Approved :: GNU General Public License v3 (GPLv3)
Classifier: Programming Language :: Python :: 3
Requires-Python: >=3.6
License-File: LICENSE
Requires-Dist: pyserial (>=3.0)
